[{"idsQuestions":[25,26],"status":"closedQuiz","projected":false,"idSession":84,"responded":[],"notResponded":[]},{"idsQuestions":[26],"status":"runningQuestion","projected":false,"idSession":89,"responded":[],"notResponded":[],"idQuestion":25,"name":"Question texte","typeQuestion":"text","question":"Comment s'appelle la plan\u00e8te o\u00f9 Mace Windu meurt","delay":0,"responses":[],"time":140},{"idsQuestions":[25,26],"status":"closedQuiz","projected":false,"idSession":92,"responded":[],"notResponded":[]}]